odoo9_addon_medical_pharmacy-9.0.1.0.0-py2.7-nspkg.pth
odoo_addons/medical_pharmacy/__openerp__.py
odoo_addons/medical_pharmacy/__init__.py
odoo_addons/medical_pharmacy/README.rst
odoo_addons/medical_pharmacy/security/ir.model.access.csv
odoo_addons/medical_pharmacy/models/__init__.py
odoo_addons/medical_pharmacy/models/medical_pharmacy.py
odoo_addons/medical_pharmacy/views/medical_menu.xml
odoo_addons/medical_pharmacy/views/medical_pharmacy_view.xml
odoo_addons/medical_pharmacy/tests/test_medical_pharmacy.py
odoo_addons/medical_pharmacy/tests/__init__.py
odoo_addons/medical_pharmacy/demo/medical_pharmacy_demo.xml
odoo_addons/medical_pharmacy/static/description/icon.png
odoo9_addon_medical_pharmacy-9.0.1.0.0.dist-info/top_level.txt
odoo9_addon_medical_pharmacy-9.0.1.0.0.dist-info/WHEEL
odoo9_addon_medical_pharmacy-9.0.1.0.0.dist-info/RECORD
odoo9_addon_medical_pharmacy-9.0.1.0.0.dist-info/metadata.json
odoo9_addon_medical_pharmacy-9.0.1.0.0.dist-info/DESCRIPTION.rst
odoo9_addon_medical_pharmacy-9.0.1.0.0.dist-info/METADATA
odoo9_addon_medical_pharmacy-9.0.1.0.0.dist-info/namespace_packages.txt
